cvpl_tools/__init__.py
cvpl_tools/examples/__init__.py
cvpl_tools/examples/mousebrain_processing.py
cvpl_tools/examples/mousebrain_processing_inspect.py
cvpl_tools/fsspec.py
cvpl_tools/im/algorithms.py
cvpl_tools/im/algs/dask_label.py
cvpl_tools/im/algs/dask_ndinterp.py
cvpl_tools/im/ndblock.py
cvpl_tools/im/process/any_to_any.py
cvpl_tools/im/process/base.py
cvpl_tools/im/process/bs_to_os.py
cvpl_tools/im/process/lc_to_cc.py
cvpl_tools/im/process/os_to_cc.py
cvpl_tools/im/process/os_to_lc.py
cvpl_tools/im/process/qsetup.py
cvpl_tools/nnunet/annotate.py
cvpl_tools/nnunet/api.py
cvpl_tools/nnunet/cli.py
cvpl_tools/nnunet/lightsheet_preprocess.py
cvpl_tools/nnunet/mwcmd.py
cvpl_tools/nnunet/n4.py
cvpl_tools/nnunet/triplanar.py
cvpl_tools/ome_zarr/io.py
cvpl_tools/ome_zarr/napari/add.py
cvpl_tools/ome_zarr/ome_zarr_writer_patched.py
cvpl_tools/tools/array_key_dict.py
cvpl_tools/tools/dask_utils.py
cvpl_tools/tools/dict_utils.py
cvpl_tools/tools/fs.py
cvpl_tools/tools/plot_utils.py
cvpl_tools/tools/test_utils/__init__.py
cvpl_tools/tools/test_utils/assert.py
cvpl_tools-1.0.0.dist-info/LICENSE
cvpl_tools-1.0.0.dist-info/METADATA
cvpl_tools-1.0.0.dist-info/WHEEL
cvpl_tools-1.0.0.dist-info/RECORD
